Metadata-Version: 2.1
Name: JsonStructor
Version: 0.0.9
Summary: The `JsonStructor` library is a Python package that simplifies the process of working with JSON files. It offers a user-friendly interface for reading, writing, and editing JSON data, making it easy to add, remove, or alter key-value pairs in a JSON file. Ideal for developers who need to interact with JSON data in their applications, `JsonStructor` streamlines common JSON operations with its straightforward and intuitive methods.
Home-page: https://github.com/KiryxaTechDev/JsonStructor
Download-URL: https://github.com/KiryxaTechDev/JsonStructor/archive/refs/tags/0.0.9.zip
Author: KiryxaTech
Author-email: kiryxatech@gmail.com
Classifier: License :: OSI Approved :: Apache Software License
Classifier: Programming Language :: Python
Classifier: Programming Language :: Python :: 3
Classifier: Programming Language :: Python :: 3.1
Classifier: Programming Language :: Python :: 3.2
Classifier: Programming Language :: Python :: 3.3
Classifier: Programming Language :: Python :: 3.4
Classifier: Programming Language :: Python :: 3.5
Classifier: Programming Language :: Python :: 3.6
Classifier: Programming Language :: Python :: 3.7
Classifier: Programming Language :: Python :: 3.8
Classifier: Programming Language :: Python :: 3.9
Classifier: Programming Language :: Python :: 3.10
Classifier: Programming Language :: Python :: 3.11
Classifier: Programming Language :: Python :: 3.12
